docs/conf.py
pyrfu/__init__.py
pyrfu/dispersion/__init__.py
pyrfu/dispersion/disp_surf_calc.py
pyrfu/dispersion/one_fluid_dispersion.py
pyrfu/lp/__init__.py
pyrfu/lp/photo_current.py
pyrfu/lp/thermal_current.py
pyrfu/maven/__init__.py
pyrfu/maven/config.json
pyrfu/maven/db_init.py
pyrfu/maven/download_data.py
pyrfu/mms/__init__.py
pyrfu/mms/ancillary.json
pyrfu/mms/calculate_epsilon.py
pyrfu/mms/config.json
pyrfu/mms/copy_files.py
pyrfu/mms/copy_files_ancillary.py
pyrfu/mms/correct_edp_probe_timing.py
pyrfu/mms/db_get_ts.py
pyrfu/mms/db_get_variable.py
pyrfu/mms/db_init.py
pyrfu/mms/def2psd.py
pyrfu/mms/dft_time_shift.py
pyrfu/mms/download_ancillary.py
pyrfu/mms/download_data.py
pyrfu/mms/dpf2psd.py
pyrfu/mms/dsl2gse.py
pyrfu/mms/dsl2gsm.py
pyrfu/mms/eis_ang_ang.py
pyrfu/mms/eis_combine_proton_pad.py
pyrfu/mms/eis_combine_proton_skymap.py
pyrfu/mms/eis_combine_proton_spec.py
pyrfu/mms/eis_moments.py
pyrfu/mms/eis_omni.py
pyrfu/mms/eis_pad.py
pyrfu/mms/eis_pad_combine_sc.py
pyrfu/mms/eis_pad_spinavg.py
pyrfu/mms/eis_proton_correction.py
pyrfu/mms/eis_skymap.py
pyrfu/mms/eis_skymap_combine_sc.py
pyrfu/mms/eis_spec_combine_sc.py
pyrfu/mms/eis_spin_avg.py
pyrfu/mms/estimate_phase_speed.py
pyrfu/mms/feeps_active_eyes.py
pyrfu/mms/feeps_bad_data.json
pyrfu/mms/feeps_correct_energies.py
pyrfu/mms/feeps_corrections.py
pyrfu/mms/feeps_energy_table.py
pyrfu/mms/feeps_flat_field_corrections.py
pyrfu/mms/feeps_omni.py
pyrfu/mms/feeps_pad.py
pyrfu/mms/feeps_pad_spinavg.py
pyrfu/mms/feeps_pitch_angles.py
pyrfu/mms/feeps_remove_bad_data.py
pyrfu/mms/feeps_remove_sun.py
pyrfu/mms/feeps_remove_sunlit_sectors.py
pyrfu/mms/feeps_sector_spec.py
pyrfu/mms/feeps_spin_avg.py
pyrfu/mms/feeps_split_integral_ch.py
pyrfu/mms/fft_bandpass.py
pyrfu/mms/fk_power_spectrum_4sc.py
pyrfu/mms/get_data.py
pyrfu/mms/get_dist.py
pyrfu/mms/get_eis_allt.py
pyrfu/mms/get_feeps_alleyes.py
pyrfu/mms/get_feeps_omni.py
pyrfu/mms/get_hpca_dist.py
pyrfu/mms/get_pitch_angle_dist.py
pyrfu/mms/get_ts.py
pyrfu-2.4.19.dist-info/licenses/LICENSE.txt
pyrfu-2.4.19.dist-info/METADATA
pyrfu-2.4.19.dist-info/WHEEL
pyrfu-2.4.19.dist-info/top_level.txt
pyrfu-2.4.19.dist-info/RECORD
