Metadata-Version: 2.4
Name: pyrfu
Version: 2.4.19
Summary: Python Space Physics (RymdFysik) Utilities
Author-email: Louis RICHARD <louir@irfu.se>
License: 
Project-URL: homepage, https://pypi.org/project/pyrfu/
Project-URL: documentation, https://pyrfu.readthedocs.io/en/latest/
Project-URL: source, https://github.com/louis-richard/irfu-python
Project-URL: issue-tracker, https://github.com/louis-richard/irfu-python/issues
Classifier: Development Status :: 2 - Pre-Alpha
Classifier: Environment :: Other Environment
Classifier: Intended Audience :: Science/Research
Classifier: License :: OSI Approved :: MIT License
Classifier: Natural Language :: English
Classifier: Operating System :: Unix
Classifier: Operating System :: MacOS
Classifier: Operating System :: MacOS :: MacOS X
Classifier: Operating System :: Microsoft
Classifier: Operating System :: Microsoft :: MS-DOS
Classifier: Operating System :: Microsoft :: Windows
Classifier: Programming Language :: Python
Classifier: Programming Language :: Python :: 3
Classifier: Programming Language :: Python :: 3 :: Only
Classifier: Programming Language :: Python :: 3.10
Classifier: Programming Language :: Python :: 3.11
Classifier: Programming Language :: Python :: 3.12
Classifier: Programming Language :: Python :: 3.13
Classifier: Programming Language :: Python :: 3.14
Classifier: Topic :: Scientific/Engineering
Classifier: Topic :: Scientific/Engineering :: Physics
Requires-Python: <3.15,>=3.10
License-File: LICENSE.txt
Requires-Dist: boto3>=1.35.0
Requires-Dist: botocore>=1.35.0
Requires-Dist: cdflib>=1.3.0
Requires-Dist: keyring>=25.5.0
Requires-Dist: keyrings.alt>=5.0.2
Requires-Dist: geopack>=1.0.10
Requires-Dist: matplotlib>=3.9.0
Requires-Dist: numba>=0.63.0
Requires-Dist: numpy<2.4,>=2.0
Requires-Dist: pandas>=2.2.3
Requires-Dist: pycdfpp>=0.7.0
Requires-Dist: python-dateutil>=2.9.0
Requires-Dist: requests>=2.32.0
Requires-Dist: scipy>=1.14.0
Requires-Dist: tqdm>=4.66.0
Requires-Dist: xarray>=2024.10.0
Provides-Extra: git
Requires-Dist: pre-commit; extra == "git"
Provides-Extra: style
Requires-Dist: black; extra == "style"
Requires-Dist: flake8; extra == "style"
Requires-Dist: isort; extra == "style"
Requires-Dist: pylint; extra == "style"
Provides-Extra: tests
Requires-Dist: ddt; extra == "tests"
Requires-Dist: pytest; extra == "tests"
Requires-Dist: pytest-cov; extra == "tests"
Provides-Extra: type-checking
Requires-Dist: mypy; extra == "type-checking"
Provides-Extra: docs
Requires-Dist: nbsphinx>=0.9.2; extra == "docs"
Requires-Dist: numpydoc>=1.5.0; extra == "docs"
Requires-Dist: pydata-sphinx-theme>=0.13.0; extra == "docs"
Requires-Dist: sphinx>=7.0.0; extra == "docs"
Requires-Dist: sphinx-codeautolink>=0.15.0; extra == "docs"
Requires-Dist: sphinx-copybutton>=0.5.0; extra == "docs"
Requires-Dist: sphinx-gallery>=0.13.0; extra == "docs"
Requires-Dist: sphinxcontrib-apidoc>=0.3.0; extra == "docs"
Provides-Extra: dev
Requires-Dist: pyrfu[docs]; extra == "dev"
Requires-Dist: pyrfu[git]; extra == "dev"
Requires-Dist: pyrfu[style]; extra == "dev"
Requires-Dist: pyrfu[tests]; extra == "dev"
Requires-Dist: pyrfu[type-checking]; extra == "dev"
Dynamic: license-file
